pep723_loader/__init__.py
pep723_loader/cli.py
pep723_loader/dependencies.py
pep723_loader/pep723_checker.py
pep723_loader/version.py
pep723_loader/tests/e2e/test_cli_e2e.py
pep723_loader/tests/unit/test_cli.py
pep723_loader/tests/unit/fixtures/empty_deps.py
pep723_loader/tests/unit/fixtures/invalid_pep723.py
pep723_loader/tests/unit/fixtures/no_deps.py
pep723_loader/tests/unit/fixtures/with_deps_no_shebang.py
pep723_loader/tests/unit/fixtures/with_deps_python_shebang.py
pep723_loader/tests/unit/fixtures/with_deps_uv_shebang.py
pep723_loader-0.8.0.dist-info/METADATA
pep723_loader-0.8.0.dist-info/WHEEL
pep723_loader-0.8.0.dist-info/entry_points.txt
pep723_loader-0.8.0.dist-info/licenses/LICENSE
pep723_loader-0.8.0.dist-info/RECORD
