Metadata-Version: 2.4
Name: pep723-loader
Version: 0.8.0
Summary: PEP 723 wrapper for linting Python scripts
Project-URL: Homepage, https://github.com/bitflight-devops/pre-commit-pep723-linter-wrapper
Project-URL: Repository, https://github.com/bitflight-devops/pre-commit-pep723-linter-wrapper
Project-URL: Issues, https://github.com/bitflight-devops/pre-commit-pep723-linter-wrapper/issues
Author-email: Jamie Nelson <jamie@bitflight.io>
Maintainer-email: Jamie Nelson <jamie@bitflight.io>
License: Apache License 2.0
License-File: LICENSE
Keywords: lint,loader,pep723,python
Classifier: Development Status :: 4 - Beta
Classifier: Intended Audience :: Developers
Classifier: License :: Public Domain
Classifier: Operating System :: POSIX :: Linux
Classifier: Programming Language :: Python :: 3
Classifier: Programming Language :: Python :: 3.10
Classifier: Programming Language :: Python :: 3.11
Classifier: Programming Language :: Python :: 3.12
Classifier: Programming Language :: Python :: 3.13
Classifier: Programming Language :: Python :: 3.14
Requires-Python: >=3.10
Requires-Dist: gitpython>=3.1.0
Requires-Dist: pydantic>=2.10.6
Requires-Dist: python-dotenv>=1.1.1
Requires-Dist: typer>=0.20.0
Requires-Dist: uv>=0.9.2
